cy_weather_api/__init__.py
cy_weather_api/client.py
cy_weather_api/models/__init__.py
cy_weather_api/models/alert.py
cy_weather_api/models/daily.py
cy_weather_api/models/hourly.py
cy_weather_api/models/minutely.py
cy_weather_api/models/realtime.py
cy_weather_api/models/result.py
cy_weather_api/models/skycon.py
cy_weather_api-0.2.2.dist-info/METADATA
cy_weather_api-0.2.2.dist-info/WHEEL
cy_weather_api-0.2.2.dist-info/licenses/LICENSE
cy_weather_api-0.2.2.dist-info/RECORD
