Metadata-Version: 2.3
Name: cy_weather_api
Version: 0.2.2
Summary: Caiyun Weather API Python SDK
Author-email: caiyunapp <oss@caiyunapp.com>
License-File: LICENSE
Requires-Python: >=3.12
Requires-Dist: dacite>=1.8.1
Requires-Dist: httpx>=0.27.2
Requires-Dist: orjson>=3.10.11
